r0b0/__init__.py
r0b0/config.py
r0b0/cables/__init__.py
r0b0/cables/blsm.py
r0b0/cables/cable.py
r0b0/cables/eink_cables.py
r0b0/cables/midi_funcs.py
r0b0/cables/mouse_funcs.py
r0b0/cables/mpi_cables.py
r0b0/cables/msg_funcs.py
r0b0/cables/ps2014.py
r0b0/cables/time_control_cables.py
r0b0/gadgets/__init__.py
r0b0/gadgets/arduino.py
r0b0/gadgets/camera.py
r0b0/gadgets/chatbot.py
r0b0/gadgets/dxl_robot.py
r0b0/gadgets/eink.py
r0b0/gadgets/gadget.py
r0b0/gadgets/language_model.py
r0b0/gadgets/mediapipe_gadget.py
r0b0/gadgets/microphone.py
r0b0/gadgets/midi_controller.py
r0b0/gadgets/mouse.py
r0b0/gadgets/page.py
r0b0/gadgets/pi_button.py
r0b0/gadgets/pi_camera.py
r0b0/gadgets/pi_gadget.py
r0b0/gadgets/pi_screen.py
r0b0/gadgets/pygame_gadget.py
r0b0/gadgets/rtc.py
r0b0/gadgets/serial_gadget.py
r0b0/gadgets/tape.py
r0b0/gadgets/tape_player.py
r0b0/gadgets/test_gadget.py
r0b0/gadgets/test_joystick.py
r0b0/gadgets/test_message.py
r0b0/gadgets/test_robot.py
r0b0/gadgets/time_controller.py
r0b0/kinematics/blsm.py
r0b0/kinematics/kinematics.py
r0b0/rigs/__init__.py
r0b0/rigs/host.py
r0b0/rigs/rig.py
r0b0/scripts/motor_calib.py
r0b0/scripts/pypot_calib.py
r0b0/utils/__init__.py
r0b0/utils/loaders.py
blsm_io-0.0.0.dist-info/LICENSE.txt
blsm_io-0.0.0.dist-info/METADATA
blsm_io-0.0.0.dist-info/WHEEL
blsm_io-0.0.0.dist-info/top_level.txt
blsm_io-0.0.0.dist-info/RECORD
