Metadata-Version: 2.1
Name: blsm-io
Version: 0.0.0
Summary: Library for connecting hardware and software, like aconnect for anything.
Author-email: Michael Suguitan <m.jp.sgtn@icloud.com>
License: MIT License
Project-URL: Repository, https://github.com/msgtn/r0b0.git
License-File: LICENSE.txt
Requires-Dist: aiohttp ==3.8.3
Requires-Dist: Flask ==2.2.2
Requires-Dist: Flask-Cors ==3.0.10
Requires-Dist: Flask-SocketIO ==5.3.2
Requires-Dist: numpy ==1.24.0
Requires-Dist: PyYAML ==6.0.1
Requires-Dist: pygame ==2.4.0
Requires-Dist: python-socketio ==5.8.0
Requires-Dist: urllib3 ==1.26.13
Requires-Dist: Werkzeug ==2.3.6
Requires-Dist: python-engineio ==4.3.4
Requires-Dist: requests ==2.31.0
Requires-Dist: eventlet ==0.34.2
Requires-Dist: websocket-client ==1.6.1
Provides-Extra: chatbot
Requires-Dist: simpleaichat ==0.2.1 ; extra == 'chatbot'
Provides-Extra: robot
